tests/__init__.py
tests/test_logger.py
tj_kits_wind/__init__.py
tj_kits_wind/tj_logger/LoggerFactory.py
tj_kits_wind/tj_logger/__init__.py
tj_kits_wind/tj_path/__init__.py
tj_kits_wind/tj_path/project_root.py
tj_kits_wind/tj_time/__init__.py
tj_kits_wind/tj_time/tj_time_tools.py
tj_kits_wind/tj_time/tt.py
tj_kits_wind-0.1.0.dist-info/METADATA
tj_kits_wind-0.1.0.dist-info/WHEEL
tj_kits_wind-0.1.0.dist-info/top_level.txt
tj_kits_wind-0.1.0.dist-info/RECORD
