Metadata-Version: 2.1
Name: tj_kits_wind
Version: 0.1.0
Summary: some kits
Home-page: https://github.com/TJNo-1/tj_kits_wind.git
Author: tjno-1
Author-email: tjno-1@qq.com
License: MIT
Keywords: python,build-in-module kits
Classifier: Programming Language :: Python :: 3.10
Classifier: License :: OSI Approved :: MIT License
Classifier: Operating System :: OS Independent
Requires: pydantic
Requires-Python: >=3.8
